LICENSE
MANIFEST.in
README.md
VERSION
requirements.txt
setup.cfg
setup.py
rhasspy_silence.egg-info/PKG-INFO
rhasspy_silence.egg-info/SOURCES.txt
rhasspy_silence.egg-info/dependency_links.txt
rhasspy_silence.egg-info/requires.txt
rhasspy_silence.egg-info/top_level.txt
rhasspysilence/__init__.py
rhasspysilence/__main__.py
rhasspysilence/const.py
rhasspysilence/py.typed
tests/__init__.py
tests/test_rhasspysilence.py